govtech_csg_xcg/dangerousfunctions/__init__.py
govtech_csg_xcg/dangerousfunctions/apps.py
govtech_csg_xcg/dangerousfunctions/patch/__init__.py
govtech_csg_xcg/dangerousfunctions/patch/functions.py
govtech_csg_xcg/dangerousfunctions/patch/patch.py
govtech_csg_xcg/dangerousfunctions/patch/template_filters.py
govtech_csg_xcg/dangerousfunctions/patch/utils.py
govtech_csg_xcg_dangerousfunctions-0.1.0.dist-info/LICENSE
govtech_csg_xcg_dangerousfunctions-0.1.0.dist-info/METADATA
govtech_csg_xcg_dangerousfunctions-0.1.0.dist-info/WHEEL
govtech_csg_xcg_dangerousfunctions-0.1.0.dist-info/top_level.txt
govtech_csg_xcg_dangerousfunctions-0.1.0.dist-info/RECORD
